yadraw/__init__.py
yadraw/yadraw.py
yadraw-0.0.20.dist-info/METADATA
yadraw-0.0.20.dist-info/WHEEL
yadraw-0.0.20.dist-info/licenses/LICENCE
yadraw-0.0.20.dist-info/RECORD
