Metadata-Version: 2.1
Name: yadraw
Version: 0.0.20
Summary: Graphical library over pygame
Project-URL: Homepage, https://github.com/EmixD/yadraw
Project-URL: Bug Tracker, https://github.com/EmixD/yadraw/issues
Author-email: "Ivan I. Yakovkin" <yakovkinii@gmail.com>
License-File: LICENCE
Classifier: License :: OSI Approved :: MIT License
Classifier: Operating System :: OS Independent
Classifier: Programming Language :: Python :: 3
Requires-Python: >=3.7
Requires-Dist: attrs
Requires-Dist: numpy
Requires-Dist: pygame
Requires-Dist: yatools
